[
  {
    "title": "Cardano (ADA.CM=) Dips 1.05% to $0.68 Amid Market Volatility",
    "summary": "Cardano (ADA.CM=) saw a modest decline, slipping 1.05% to trade at $0.68 as of 10:03 PM EDT. This downturn reflects ongoing market volatility impacting altcoins, possibly influenced by broader crypto sentiment and macroeconomic factors.\n\nInvestors may want to monitor ADA closely, as its price movement could signal short-term pressures or consolidation phases ahead. For those tracking live updates, real-time quotes are available to stay informed on Cardano's evolving position in the crypto market.\n\nhttps://www.cnbc.com/quotes/ADA.CM=\n",
    "link": "",
    "image_url": null,
    "timestamp": "2025-06-02T02:04:00.513807"
  },
  {
    "title": "DOT.CM= slips 1.08% to $4.06 amid cautious market sentiment",
    "summary": "Polkadot (DOT.CM=) experienced a modest pullback, closing at $4.06, down 1.08% as of 10:03 PM EDT. This slight decline reflects a cautious investor stance amid broader market uncertainties impacting the cryptocurrency sector.\n\nDespite the dip, Polkadot remains a significant player in the blockchain ecosystem, with its innovative approach to interoperability continuing to attract long-term interest. Traders and investors should monitor upcoming developments and market trends that could influence its trajectory.\n\nFor those seeking real-time updates and detailed price movements, the live tracking link below provides comprehensive market data.\n\nhttps://www.cnbc.com/quotes/DOT.CM=\n",
    "link": "",
    "image_url": null,
    "timestamp": "2025-06-02T02:03:53.593899"
  }
]